{
  "miniprogramRoot": "miniprogram/",
  "cloudfunctionRoot": "cloudfunctions/",
  "setting": {
    "urlCheck": true,
    "es6": true,
    "enhance": true,
    "postcss": true,
    "minified": true,
    "newFeature": true,
    "coverView": true,
    "nodeModules": false,
    "autoAudits": false,
    "showShadowRootInWxmlPanel": true,
    "scopeDataCheck": false,
    "checkInvalidKey": true,
    "checkSiteMap": true,
    "uploadWithSourceMap": true,
    "useMultiFrameRuntime": true,
    "useApiHook": true,
    "useApiHostProcess": true,
    "babelSetting": {
      "ignore": [],
      "disablePlugins": [],
      "outputPath": ""
    },
    "enableEngineNative": false,
    "useIsolateContext": true,
    "packNpmManually": false,
    "minifyWXSS": true,
    "minifyWXML": true,
    "ignoreUploadUnusedFiles": true,
    "compileWorklet": false,
    "uglifyFileName": false,
    "packNpmRelationList": [],
    "localPlugins": false,
    "disableUseStrict": false,
    "useCompilerPlugins": false,
    "condition": false,
    "swc": false,
    "disableSWC": true
  },
  "appid": "wx1903fa52ed9fd6b2",
  "projectname": "晓医-智能导诊助手",
  "libVersion": "2.20.1",
  "compileType": "miniprogram",
  "packOptions": {
    "ignore": [],
    "include": []
  },
  "condition": {},
  "editorSetting": {
    "tabIndent": "insertSpaces",
    "tabSize": 2
  },
  "simulatorPluginLibVersion": {}
}